{
    "surah_name": "An-Nâs",
    "surah_name_ar": "الناس",
    "verses": {
        "languages": {
            "albanian": {
                "translators": {
                    "1": {
                        "Efendi Nahi": {
                            "verse 114:1": "Thuaj: “I lutem dhe i mbështetem Zotit të njerëzve,",
                            "verse 114:2": "Sundimtarit të njerëzve,",
                            "verse 114:3": "Perëndisë së njerëzve,",
                            "verse 114:4": "nga sherri i djallit, bezdisës,",
                            "verse 114:5": "i cili fshehurazi hedh dyshime në shpirtërat e njerëzve –",
                            "verse 114:6": "prej xhindëve dhe prej njerëzve!” –"
                        }
                    }
                }
            },
            "azerbaijani": {
                "translators": {
                    "1": {
                        "null": {
                            "verse 114:1": "(Ya Peyğəmbər!) De: \"Pənah aparıram insanların Rəbbinə;",
                            "verse 114:2": "İnsanların ixtiyar sahibinə;",
                            "verse 114:3": "İnsanların tanrısına;",
                            "verse 114:4": "Vəsvəsə verən, (Allahın adı çəkiləndə isə qorxusundan) qaçıb gizlənən Şeytanın şərindən-",
                            "verse 114:5": "O Şeytan ki, insanların ürəklərinə vəsvəsə salır,",
                            "verse 114:6": "(O Şeytan ki) cinlərdən də olur, insanlardan da! [Və ya: (o Şeytan) istər cinlərdən olsun, istər insanlardan!]\""
                        }
                    }
                }
            },
            "bosnian": {
                "translators": {
                    "1": {
                        "null": {
                            "verse 114:1": "Reci: \"Tražim zaštitu Gospodara ljudi,",
                            "verse 114:2": "Vladara ljudi,",
                            "verse 114:3": "Boga ljudi,",
                            "verse 114:4": "od zla šejtana napasnika,",
                            "verse 114:5": "koji zle misli unosi u srca ljudi -",
                            "verse 114:6": "od džina i od ljudi!\" -"
                        }
                    }
                }
            },
            "bengali": {
                "translators": {
                    "1": {
                        "null": {
                            "verse 114:1": "বলুন, আমি আশ্রয় গ্রহণ করিতেছি মানুষের পালনকর্তার,",
                            "verse 114:2": "মানুষের অধিপতির,",
                            "verse 114:3": "মানুষের মা’বুদের",
                            "verse 114:4": "তার অনিষ্ট থেকে, যে কুমন্ত্রণা দেয় ও আত্নগোপন করে,",
                            "verse 114:5": "যে কুমন্ত্রণা দেয় মানুষের অন্তরে",
                            "verse 114:6": "জ্বিনের মধ্য থেকে অথবা মানুষের মধ্য থেকে। অন্তরে"
                        }
                    }
                }
            },
            "bulgarian": {
                "translators": {
                    "1": {
                        "Tzvetan Theophanov": {
                            "verse 114:1": "Кажи [о, Мухаммад]: Опазил ме Господът на хората,",
                            "verse 114:2": "Владетелят на хората,",
                            "verse 114:3": "Богът на хората,",
                            "verse 114:4": "от злото на шепнещия съблазни ,",
                            "verse 114:5": "побягващия,",
                            "verse 114:6": "който нашепва в гърдите на хората,",
                            "verse 114:7": "",
                            "verse 114:8": "от джиновете и от хората!"
                        }
                    }
                }
            },
            "chinese": {
                "translators": {
                    "1": {
                        "null": {
                            "verse 114:1": "你說 :我求庇于世人的主宰 ,",
                            "verse 114:2": "世人的君王 ,",
                            "verse 114:3": "世人的神明 ,",
                            "verse 114:4": "免遭潛伏的教唆者的毒害 ,",
                            "verse 114:5": "他在世人的胸中教唆 ,",
                            "verse 114:6": "他是屬于精靈和人類的。 ,"
                        }
                    }
                }
            },
            "czech": {
                "translators": {
                    "1": {
                        "null": {
                            "verse 114:1": "Rci: \"Utíkám se v ochranu Pána lidí,",
                            "verse 114:2": "vládce lidí,",
                            "verse 114:3": "Boha lidí,",
                            "verse 114:4": "před zlem našeptavače pokradmého,",
                            "verse 114:5": "jenž našeptává do hrudi lidí,",
                            "verse 114:6": "ať již je z džinů či z lidí! lidí,"
                        }
                    }
                }
            },
            "dutch": {
                "translators": {
                    "1": {
                        "null": {
                            "verse 114:1": "Zeg: \"Ik zoek mijn toevlucht bij de Heer der mensen,",
                            "verse 114:2": "De Koning der mensen,",
                            "verse 114:3": "De God der mensen.",
                            "verse 114:4": "Opdat Hij mij bevrijd van het kwade der inblazingen van de duivel.",
                            "verse 114:5": "Die in het hart der mensen fluistert",
                            "verse 114:6": "Vanuit het midden der djinn en mensen."
                        }
                    }
                }
            },
            "english": {
                "translators": {
                    "1": {
                        "Marmaduke Pickthall": {
                            "verse 114:1": "Say: I seek refuge in the Lord of mankind,",
                            "verse 114:2": "The King of mankind,",
                            "verse 114:3": "The God of mankind,",
                            "verse 114:4": "From the evil of the sneaking whisperer,",
                            "verse 114:5": "Who whispereth in the hearts of mankind,",
                            "verse 114:6": "Of the jinn and of mankind."
                        }
                    },
                    "2": {
                        "Abdullah Yusuf Ali": {
                            "verse 114:1": "Say: I seek refuge with the Lord and Cherisher of Mankind,",
                            "verse 114:2": "The King (or Ruler) of Mankind,",
                            "verse 114:3": "The God (or judge) of Mankind,-",
                            "verse 114:4": "From the mischief of the Whisperer (of Evil), who withdraws (after his whisper),-",
                            "verse 114:5": "(The same) who whispers into the hearts of Mankind,-",
                            "verse 114:6": "Among Jinns and among men."
                        }
                    },
                    "3": {
                        "Arthur J. Arberry": {
                            "verse 114:1": "Say: ’I take refuge with the Lord of men,",
                            "verse 114:2": "the King of men,",
                            "verse 114:3": "the God of men,",
                            "verse 114:4": "from the evil of the slinking whisperer",
                            "verse 114:5": "who whispers in the breasts of men",
                            "verse 114:6": "of jinn and men."
                        }
                    },
                    "4": {
                        "Muhammad Asad": {
                            "verse 114:1": "SAY: \"I seek refuge with the Sustainer of men,",
                            "verse 114:2": "\"the Sovereign of men,",
                            "verse 114:3": "\"the God of men,",
                            "verse 114:4": "\"from the evil of the whispering, elusive tempter",
                            "verse 114:5": "\"who whispers in the hearts of men –",
                            "verse 114:6": "\"from all [temptation to evil by] invisible forces as well as men."
                        }
                    },
                    "5": {
                        "Martin Lings": {
                            "verse 114:1": "Say: I take refuge in the Lord of men.",
                            "verse 114:2": "",
                            "verse 114:3": "The King of men.",
                            "verse 114:4": "",
                            "verse 114:5": "The God of men.",
                            "verse 114:6": "",
                            "verse 114:7": "From the evil of insidious Whisper.",
                            "verse 114:8": "the evil of the stealthy whisperer.",
                            "verse 114:9": "Who whispereth in the breasts of men.",
                            "verse 114:10": "",
                            "verse 114:11": "From jinn and men.",
                            "verse 114:12": "Sources",
                            "verse 114:13": "Used• Unpublished Material (1938-2005) BOOKS•",
                            "verse 114:14": "The Book of Certainty (1952) •",
                            "verse 114:15": "A Sufi Saint of the Twentieth Century (1961) •",
                            "verse 114:16": "What is Sufism (1975) •",
                            "verse 114:17": "The Quranic Art of Calligraphy and Illumination (1976) •",
                            "verse 114:18": "Muhammad (1983) •",
                            "verse 114:19": "Symbol and Archetype (1991) •",
                            "verse 114:20": "Sufi Poems (2004) •",
                            "verse 114:21": "Mecca (2004) •",
                            "verse 114:22": "Return to the Spirit (2005) •",
                            "verse 114:23": "Splendours of Qur’an Calligraphy and Illumination (2005) ARTICLES•",
                            "verse 114:24": "“Proofs of Islam”(1954).",
                            "verse 114:25": "“The Islamic and Christian Conceptions of the March of Time” (1954) The Islamic Quarterly, Vol.",
                            "verse 114:26": "“The Origins of Sufism (1956) The Islamic Quarterly, Vol.",
                            "verse 114:27": "“Sufism”: Religion in the Middle East (1969); ed.",
                            "verse 114:28": "“Sufi Answers to Questions On Ultimate Reality”: Studies in Comparative Religions 1979 Summer/Autumn •",
                            "verse 114:29": "“The Nature and Origin of Sufism”: Islamic Spirituality (1985) •",
                            "verse 114:30": "“Mystical Poetry”: The Cambridge History of Arabic Literature, Vol.",
                            "verse 114:31": "“The Quranic Doctrine of the Afterlife” •",
                            "verse 114:32": "“The Quranic Origins of Sufism” •",
                            "verse 114:33": "“Human Origins and Destinies According to the Great Religions of the World” •",
                            "verse 114:34": "“Metaphysics and the Perennial Philosophy” •",
                            "verse 114:35": "“An Introduction to Islam” •",
                            "verse 114:36": "“The Universality of the Quran” •",
                            "verse 114:37": "Private Talks Books",
                            "verse 114:38": "without Quranic Ayaat• Collected Poems• Ancient Beliefs and Modern Superstitions• The Eleventh Hour• The Secret of ShakespeareArticles without Quranic Ayaat• “Signs of the Times”: Studies in Comparative Religions 1970 Winter• “Ibn Aliwah” Encyclopedia of Islam, Second Edition• “Kabd” Encyclopedia of Islam, Second Edition Books"
                        }
                    },
                    "6": {
                        "Mufti Muhammad Taqi Uthmani": {
                            "verse 114:1": "Say, “I seek refuge with the Lord of mankind,",
                            "verse 114:2": "the King of mankind,",
                            "verse 114:3": "the God of mankind,",
                            "verse 114:4": "from the evil of the whisperer who withdraws (when Allah’s name is pronounced),",
                            "verse 114:5": "the one who whispers in the hearts of people,",
                            "verse 114:6": "whether from among the Jinn or Mankind."
                        }
                    },
                    "7": {
                        "Royal Aal al-Bayt Institute Translation": {
                            "verse 114:1": "Say: ‘I seek refuge in the Lord of mankind,",
                            "verse 114:2": "the King of mankind,",
                            "verse 114:3": "the God of mankind,",
                            "verse 114:4": "from the evil of the slinking whisperer,",
                            "verse 114:5": "who whispers in the breasts of mankind,",
                            "verse 114:6": "of the jinn and mankind’."
                        }
                    },
                    "8": {
                        "Recitations of Ibrahim walk from saheeh international": {
                            "verse 114:1": "Beseech: ‘I seek refuge with the Lord of (the whole of) mankind,",
                            "verse 114:2": "Who is the King of (all) mankind,",
                            "verse 114:3": "Who is the God of the (whole) human race,",
                            "verse 114:4": "From the evil of the slinking whisperer (Satan) who hides himself withdrawing (from the influence of Allah’s remembrance),",
                            "verse 114:5": "Who whispers into the hearts of mankind,",
                            "verse 114:6": "Whether he (the whispering Satan) comes from the jinn or mankind."
                        }
                    }
                }
            },
            "finnish": {
                "translators": {
                    "1": {
                        "null": {
                            "verse 114:1": "Sano: »Minä etsin turvaa ihmisten Herralta,",
                            "verse 114:2": "ihmisten Kuninkaalta,",
                            "verse 114:3": "ihmisten Jumalalta,",
                            "verse 114:4": "hiipijän pahoja kuiskauksia vastaan,",
                            "verse 114:5": "hänen, joka herättää pahuutta ihmismielissä,",
                            "verse 114:6": "olkoonpa hän paholaisten tai ihmisten joukosta."
                        }
                    }
                }
            },
            "french": {
                "translators": {
                    "1": {
                        "Jean-Louis Michon": {
                            "verse 114:1": "Dis : \" Je prends refuge auprès du Seigneur des hommes,",
                            "verse 114:2": "Roi des hommes,",
                            "verse 114:3": "Dieu des hommes,",
                            "verse 114:4": "contre le mal du tentateur sournois",
                            "verse 114:5": "qui susurre le mal dans la poitrine des hommes,",
                            "verse 114:6": "contre les djinns et contre les hommes ! \" hommes,"
                        }
                    },
                    "2": {
                        "Muhammad Hamidullah ": {
                            "verse 114:1": "Dis : «Je cherche protection auprès du Seigneur des hommes.",
                            "verse 114:2": "Le Souverain des hommes,",
                            "verse 114:3": "Dieu des hommes,",
                            "verse 114:4": "contre le mal du mauvais conseiller, furtif,",
                            "verse 114:5": "qui souffle le mal dans les poitrines des hommes,",
                            "verse 114:6": "qu’il (le conseiller) soit un djinn, ou un être humain»."
                        }
                    }
                }
            },
            "german": {
                "translators": {
                    "1": {
                        "null": {
                            "verse 114:1": "Sprich: «Ich nehme meine Zuflucht beim Herrn der Menschen,",
                            "verse 114:2": "Dem König der Menschen,",
                            "verse 114:3": "Dem Gott der Menschen,",
                            "verse 114:4": "Vor dem Übel des schleichenden Einflüsterers -",
                            "verse 114:5": "Der da einflüstert in die Herzen der Menschen -",
                            "verse 114:6": "Unter den Dschinn und den Menschen."
                        }
                    }
                }
            },
            "hindi": {
                "translators": {
                    "1": {
                        "null": {
                            "verse 114:1": "¼,s jlwy½ rqe dg nks eSa yksxksa ds ijojfnxkj",
                            "verse 114:2": "yksxksa ds ckn’kkg",
                            "verse 114:3": "yksxksa ds ekcwn dh ¼ÓSrkuh½",
                            "verse 114:4": "olols dh cqjkbZ ls iukg ek¡xrk gw¡",
                            "verse 114:5": "tks ¼[+kqnk ds uke ls½ ihNs gV tkrk gS tks yksxksa ds fnyksa esa olols Mkyk djrk gS",
                            "verse 114:6": "ftUukr esa ls [+okg vknfe;ksa esa ls"
                        }
                    }
                }
            },
            "indonesian": {
                "translators": {
                    "1": {
                        "null": {
                            "verse 114:1": "Katakanlah: \"Aku berlindung kepada Tuhan (yang memelihara dan menguasai) manusia.",
                            "verse 114:2": "Raja manusia.",
                            "verse 114:3": "Sembahan manusia.",
                            "verse 114:4": "dari kejahatan (bisikan) setan yang biasa bersembunyi,",
                            "verse 114:5": "yang membisikkan (kejahatan) ke dalam dada manusia.",
                            "verse 114:6": "dari (golongan) jin dan manusia."
                        }
                    }
                }
            },
            "italian": {
                "translators": {
                    "1": {
                        "null": {
                            "verse 114:1": "Di': \" Mi rifugio nel Signore degli uomini,",
                            "verse 114:2": "Re degli uomini,",
                            "verse 114:3": "Dio degli uomini,",
                            "verse 114:4": "contro il male del sussurratore furtivo,",
                            "verse 114:5": "che soffia il male nei cuori degli uomini,",
                            "verse 114:6": "che",
                            "verse 114:7": "dai dèmoni o dagli uomini\"."
                        }
                    }
                }
            },
            "japanese": {
                "translators": {
                    "1": {
                        "null": {
                            "verse 114:1": "言え，「ご加護を乞い願う，人間の主，",
                            "verse 114:2": "人間の王，",
                            "verse 114:3": "人間の神に。",
                            "verse 114:4": "こっそりと忍び込み，囁く者の悪から。",
                            "verse 114:5": "それが人間の胸に囁きかける，",
                            "verse 114:6": "ジン（幽精）であろうと，人間であろうと。」 それが人間の胸に囁きかける，"
                        }
                    }
                }
            },
            "korean": {
                "translators": {
                    "1": {
                        "null": {
                            "verse 114:1": "일러가로되 인류의 주님께 보호를 구하고",
                            "verse 114:2": "인류의 왕이며",
                            "verse 114:3": "인류의 신에게",
                            "verse 114:4": "인간의 흉중에 도사리는 사탄 와 재앙을",
                            "verse 114:5": "인간의 가슴속에서 유혹하는 사탄의 유혹을",
                            "verse 114:6": "영마와 인간의 유혹으로부터 보호를 구하나이다"
                        }
                    }
                }
            },
            "kurdish": {
                "translators": {
                    "1": {
                        "null": {
                            "verse 114:1": "(ئه‌ی محمد (صلی الله علیه وسلم) ئه‌ی ئیماندار) بڵێ: په‌نا ده‌گرم به په‌روه‌ردگاری خه‌ڵکی.",
                            "verse 114:2": "پادشای خه‌ڵکی",
                            "verse 114:3": "به خوای خه‌ڵکی.",
                            "verse 114:4": "له شه‌ڕ و خراپه‌ی ئه‌وه‌ی که وه‌سوه‌سه و خه‌ته‌ره و خه‌یاڵ ده‌خاته دڵه‌وه که (خه‌ناسه‌).",
                            "verse 114:5": "له په‌ری و خه‌ڵکی، له جنۆکه و ئاده‌میزاد (ئه‌وانه‌ی که شه‌یتان سیفه‌تن).",
                            "verse 114:6": "له په‌ری و خه‌ڵكی (له جنۆكه و ئینسان ئه‌وانه‌ی شه‌یتان سیفه‌تن)."
                        }
                    }
                }
            },
            "malay": {
                "translators": {
                    "1": {
                        "null": {
                            "verse 114:1": "Katakanlah (wahai Muhammad): Aku berlindung kepada (Allah) Pemelihara sekalian manusia.",
                            "verse 114:2": "Yang Menguasai sekalian manusia,",
                            "verse 114:3": "Tuhan yang berhak disembah oleh sekalian manusia,",
                            "verse 114:4": "Dari kejahatan pembisik penghasut yang timbul tenggelam, -",
                            "verse 114:5": "Yang melemparkan bisikan dan hasutannya ke dalam hati manusia, -",
                            "verse 114:6": "(Iaitu pembisik dan penghasut) dari kalangan jin dan manusia."
                        }
                    }
                }
            },
            "persian": {
                "translators": {
                    "1": {
                        "null": {
                            "verse 114:1": "بگو: پناه مى‏برم به پروردگار مردم،",
                            "verse 114:2": "به مالك و حاكم مردم،",
                            "verse 114:3": "به (خدا و) معبود مردم،",
                            "verse 114:4": "از شر وسوسه‏گر پنهانكار،",
                            "verse 114:5": "كه در درون سينه انسانها وسوسه مى‏كند،",
                            "verse 114:6": "خواه از جن باشد يا از انسان!"
                        }
                    }
                }
            },
            "portuguese": {
                "translators": {
                    "1": {
                        "null": {
                            "verse 114:1": "Dize: Amparo-me no Senhor dos humanos,",
                            "verse 114:2": "O Rei dos humanos,",
                            "verse 114:3": "O Deus dos humanos,",
                            "verse 114:4": "Contra o mal do sussurro do malfeitor,",
                            "verse 114:5": "Que sussurra aos corações dos humanos,",
                            "verse 114:6": "Entre gênios e humanos!"
                        }
                    }
                }
            },
            "romanian": {
                "translators": {
                    "1": {
                        "Lucrarea (traducere úi editare) a fost realizată de către": {
                            "verse 114:1": "Spune: \"Eu caut adãpost la Domnul oamenilor,",
                            "verse 114:2": "Stãpânul oamenilor,",
                            "verse 114:3": "Dumnezeul oamenilor",
                            "verse 114:4": "Împotriva rãului ademenitorului fugar",
                            "verse 114:5": "Care șoptește în piepturile oamenilor,",
                            "verse 114:6": "Dintre djinni și oameni\"."
                        }
                    },
                    "2": {
                        "George Grigore, Coranul": {
                            "verse 114:1": "Spune: “Izbăvire caut la Domnul oamenilor,",
                            "verse 114:2": "Regele oamenilor,",
                            "verse 114:3": "Dumnezeul oamenilor,",
                            "verse 114:4": "de răul şoptitorului-furişătorului,",
                            "verse 114:5": "cel care şopteşte răul în inimile oamenilor,",
                            "verse 114:6": "fie el dintre ginni ori dintre oameni!” oamenilor,"
                        }
                    }
                }
            },
            "russian": {
                "translators": {
                    "1": {
                        "null": {
                            "verse 114:1": "Скажи: «Ищу спасенья я у Господалюдей,",
                            "verse 114:2": "Властителя людей,",
                            "verse 114:3": "У Бога человеческого рода",
                            "verse 114:4": "От зла недоброго смутьяна,Что, наущая, исчезает, —",
                            "verse 114:5": "Кто смуту вноситВ сердце человека",
                            "verse 114:6": "И обитает среди джиннов и людей»."
                        }
                    }
                }
            },
            "spanish": {
                "translators": {
                    "1": {
                        "null": {
                            "verse 114:1": "Di: «Me refugio en el Señor de los hombres,",
                            "verse 114:2": "el Rey de los hombres,",
                            "verse 114:3": "el Dios de los hombres,",
                            "verse 114:4": "del mal de la insinuación, del que se escabulle,",
                            "verse 114:5": "que insinúa en el ánimo de los hombres,",
                            "verse 114:6": "sea genio, sea hombre»."
                        }
                    }
                }
            },
            "tamil": {
                "translators": {
                    "1": {
                        "null": {
                            "verse 114:1": "(நபியே!) நீர் கூறுவீராக: மனிதர்களின் இறைவனிடத்தில் நான் காவல் தேடுகிறேன்.",
                            "verse 114:2": "(அவனே) மனிதர்களின் அரசன்;",
                            "verse 114:3": "(அவனே) மனிதர்களின் நாயன்.",
                            "verse 114:4": "பதுங்கியிருந்து வீண் சந்தேகங்களை உண்டாக்குபவனின் தீங்கை விட்டும் (இறைவனிடத்தில் நான் காவல் தேடுகிறேன்).",
                            "verse 114:5": "அவன் மனிதர்களின் இதயங்களில் வீண் சந்தேகங்களை உண்டாக்குகிறான்.",
                            "verse 114:6": "(இத்தகையோர்) ஜின்களிலும், மனிதர்களிலும் இருக்கின்றனர்."
                        }
                    }
                }
            },
            "thai": {
                "translators": {
                    "1": {
                        "null": {
                            "verse 114:1": "จงกล่าวเถิดมุฮัมมัด ข้าพระองค์ขอความคุ้มครอง ต่อพระเจ้าแห่งมนุษยชาติ",
                            "verse 114:2": "พระราชาแห่งมนุษยชาติ",
                            "verse 114:3": "พระเป็นเจ้าแห่งมนุษยชาติ",
                            "verse 114:4": "ให้พ้นจากความชั่วร้าย ของผู้กระซิบกระซาบที่หลอกล่อ",
                            "verse 114:5": "ที่กระซิบกระซาบในหัวอกของมนุษย์",
                            "verse 114:6": "จากหมู่ญินและมนุษย์ (หมายเหตุ: เสร็จสิ้นด้วยพระประสงค์ของอัลลอฮฺ หากพบคำผิดพลาดโปรดติดต่อเว็บไซต์มุสลิมไทยดอทคอม)"
                        }
                    }
                }
            },
            "turkish": {
                "translators": {
                    "1": {
                        "null": {
                            "verse 114:1": "De ki: Sığınırım ben insanların Rabbine,",
                            "verse 114:2": "İnsanların Melikine (mutlak sahip ve hakimine),",
                            "verse 114:3": "İnsanların İlâhına.",
                            "verse 114:4": "O sinsi vesvesenin şerrinden,",
                            "verse 114:5": "O ki insanların göğüslerine (kötü düşünceler)fısıldar.",
                            "verse 114:6": "Gerek cinlerden,gerek insanlardan(olan bütün vesvesecilerin şerrinden Allah'a sığınırım!"
                        }
                    }
                }
            },
            "urdu": {
                "translators": {
                    "1": {
                        "null": {
                            "verse 114:1": "کہو کہ میں لوگوں کے پروردگار کی پناہ مانگتا ہوں",
                            "verse 114:2": "آپ عرض کيجئے کہ ميں (سب) انسانوں کے رب کي پناہ مانگتا ہوںo",
                            "verse 114:3": "جو (سب) لوگوں کا بادشاہ ہےo",
                            "verse 114:4": "(یعنی) لوگوں کے حقیقی بادشاہ کی",
                            "verse 114:5": "لوگوں کے معبود برحق کی",
                            "verse 114:6": "جو (ساري) نسلِ انساني کا معبود ہےo",
                            "verse 114:7": "وسوسہ انداز (شيطان) کے شر سے جو (ا? کے ذکر کے اثر سے) پيچھے ہٹ کر چھپ جانے والا ہےo",
                            "verse 114:8": "(شیطان) وسوسہ انداز کی برائی سے جو (خدا کا نام سن کر) پیچھے ہٹ جاتا ہے",
                            "verse 114:9": "جو لوگوں کے دلوں میں وسوسے ڈالتا ہے",
                            "verse 114:10": "جو لوگوں کے دلوں ميں وسوسہ ڈالتا ہےo",
                            "verse 114:11": "خواہ وہ (وسوسہ انداز شيطان) جنات ميں سے ہو يا انسانوں ميں سےo",
                            "verse 114:12": "(خواہ) وہ جنّات میں \u0001 سےo"
                        }
                    }
                }
            },
            "uzbek": {
                "translators": {
                    "1": {
                        "null": {
                            "verse 114:1": "Одамлар Роббисидан.",
                            "verse 114:2": "Одамлар Подшоҳидан.",
                            "verse 114:3": "Одамлар Илоҳидан паноҳ сўрайман.",
                            "verse 114:4": "Беркиниб, кўриниб турувчи васвоснинг.",
                            "verse 114:5": "Одамлар қалбига васваса соладиганнинг.",
                            "verse 114:6": "Жинлардан ва одамлардан бўлганнинг ёмонлигидан, деб айт."
                        }
                    }
                }
            }
        }
    }
}